Metadata-Version: 1.1
Name: datagovernance
Version: 0.1
Summary: A very basic cleaning data
Home-page: UNKNOWN
Author: vignesh
Author-email: marilike007@gmail.com
License: MIT
Keywords: cleaning
Platform: UNKNOWN
Classifier: Development Status :: 5 - Production/Stable
Classifier: Intended Audience :: Education
Classifier: Operating System :: Microsoft :: Windows :: Windows 10
Classifier: License :: OSI Approved :: MIT License
Classifier: Programming Language :: Python :: 3
